{
  "base_price": 1950,
  "beamstation_catalog_url": "https://beamstation.com/datasets",
  "beamstation_origin": "https://beamstation.com",
  "category_group_name": "Restaurants",
  "config_category": "census",
  "config_description": "Detailed restaurant dataset for Davie, Florida with a population of over 105k. Filtered by the Restaurants category group with verified business profiles, review sentiment, competitive analysis, and contact information. Refreshed weekly.",
  "config_name": "All Restaurants in Davie, Florida, US",
  "export_job_id": "ef7a30f7-2869-43da-892a-ab09be09cf38",
  "github_org": "Beamstation-Datasets",
  "id_short": 118074,
  "location_name": "Davie",
  "location_type": "city",
  "repo_name": "all-restaurants-in-davie-florida-us-sample-118074",
  "sample_b2_path": "b2-export:BeamStation-ExportFiles/118074/beamstation_118074_restaurants-us-fl_SAMPLE_DIST.csv",
  "sample_pct": 10.0,
  "sample_records": 7,
  "sample_sha256": "87902a7e1cb0f7275b6d2beecd4b826a0042db140a496447f24d8da1d28cb7f3",
  "sample_size_bytes": 38148,
  "total_records": 70,
  "updated_at": "2026-04-30T22:07:43.115000+00:00"
}